pygumroad/__init__.py
pygumroad/core.py
pygumroad/helpers.py
pygumroad-0.0.3.dist-info/LICENSE
pygumroad-0.0.3.dist-info/METADATA
pygumroad-0.0.3.dist-info/WHEEL
pygumroad-0.0.3.dist-info/top_level.txt
pygumroad-0.0.3.dist-info/RECORD
