Metadata-Version: 2.1
Name: pygumroad
Version: 0.0.3
Summary: A Python API client for interacting with the Gumroad API.
Home-page: https://github.com/opsdisk/pygumroad
Author: Brennon Thomas
Author-email: info@opsdisk.com
License: GNU General Public License v3.0
Keywords: python gumroad api client
Platform: UNKNOWN
Requires-Python: >=3.6
License-File: LICENSE
Requires-Dist: requests-toolbelt >=1.0.0
Requires-Dist: requests >=2.24.0
